testfinder.py
testfinder-0.0.2.dist-info/entry_points.txt
testfinder-0.0.2.dist-info/LICENSE
testfinder-0.0.2.dist-info/WHEEL
testfinder-0.0.2.dist-info/METADATA
testfinder-0.0.2.dist-info/RECORD
