Metadata-Version: 2.1
Name: testfinder
Version: 0.0.2
Summary: Find test cases on a Python project.
License: MIT
Keywords: pytest,django,testing
Author: Sid Mitra
Author-email: testfinder@sidmitra.com
Requires-Python: >=3.9,<4.0
Classifier: License :: OSI Approved :: MIT License
Classifier: Programming Language :: Python :: 3
Classifier: Programming Language :: Python :: 3.9
